<?xml version="1.0" encoding="utf-8"?>
<LanguageData>

  <!-- Nod Rifle -->

  <Bullet_NodRifle.label>bullet</Bullet_NodRifle.label>

  <Gun_NodRifle.label>Nod rifle</Gun_NodRifle.label>
  <Gun_NodRifle.description>A general-purpose military weapon for field or urban combat. Specialized by Nod technology.</Gun_NodRifle.description>


  <!-- Nod Laser Rifle -->

  <Bullet_LaserRifle.label>laser</Bullet_LaserRifle.label>

  <Gun_NodLaserRifleSmall.label>Nod laser rifle</Gun_NodLaserRifleSmall.label>
  <Gun_NodLaserRifleSmall.description>A rifle using Nod's specialized laser technology.</Gun_NodLaserRifleSmall.description>

  <Gun_NodLaserRifleSmall_Faction.label>Nod Laser Rifle</Gun_NodLaserRifleSmall_Faction.label>

  <Gun_NodLaserRifleLarge.label>Nod advanced laser rifle</Gun_NodLaserRifleLarge.label>
  <Gun_NodLaserRifleLarge.description>A rifle using Nod's advanced specialized laser technology.</Gun_NodLaserRifleLarge.description>

  <Gun_NodLaserRifleLarge_Faction.label>Nod Advanced Laser Rifle</Gun_NodLaserRifleLarge_Faction.label>


  <!-- Flamethrower -->

  <Bullet_Flamethrower.label>flame</Bullet_Flamethrower.label>

  <Gun_NodFlamethrower.label>Nod flamethrower</Gun_NodFlamethrower.label>
  <Gun_NodFlamethrower.description>A Blackhand flamethrower. Cleanse the your opponents!</Gun_NodFlamethrower.description>

  <Gun_NodFlamethrower_Faction.label>Nod Flamethrower</Gun_NodFlamethrower_Faction.label>


  <!-- Nod RocketLauncher -->

  <Bullet_NodRocket.label>rocket</Bullet_NodRocket.label>

  <Gun_NodRocketLauncher.label>Nod rocket launcher</Gun_NodRocketLauncher.label>
  <Gun_NodRocketLauncher.description>A rocket launcher developed by Nod engineers. It is highly lethal.</Gun_NodRocketLauncher.description>

  <Gun_NodRocketLauncher_Faction.label>Nod Rocket Launcher</Gun_NodRocketLauncher_Faction.label>


  <!-- Twin Tiberium Flechette Gun -->

  <Bullet_Nod_TwinFlechetteGun.label>tiberium flechette</Bullet_Nod_TwinFlechetteGun.label>

  <Gun_Nod_TwinTiberiumFlechetteGun.label>Twin Flechette Gun</Gun_Nod_TwinTiberiumFlechetteGun.label>
  <Gun_Nod_TwinTiberiumFlechetteGun.description>The Tiberium Flechette gun fires Tiberium crystals rapidly at enemies.</Gun_Nod_TwinTiberiumFlechetteGun.description>


  <!-- Chemicalthrower -->

  <Bullet_Gas.label>gas cloud</Bullet_Gas.label>

  <Gun_NodChemicalthrower.label>Nod Chemical Thrower</Gun_NodChemicalthrower.label>
  <Gun_NodChemicalthrower.description>The chemical thrower is an advcanced and highly toxic weapon using Nod's liquid Tiberium technology.</Gun_NodChemicalthrower.description>

  <Gun_NodChemicalthrower_Faction.label>Nod Chemical Thrower</Gun_NodChemicalthrower_Faction.label>


  <!-- Nod Grenade -->

  <bullet_Nod_Grenade.label>grenade</bullet_Nod_Grenade.label>

  <Nod_Grenade.label>Nod Grenade</Nod_Grenade.label>
  <Nod_Grenade.description>Nod's special grenades, just as lethal as ordinary ones.</Nod_Grenade.description>


  <!-- Nod Suicide bomb -->

  <Bullet_Sbomb.label>Suicide bomb</Bullet_Sbomb.label>

  <Nod_Sbomb.label>Suicide bomb</Nod_Sbomb.label>
  <Nod_Sbomb.description>Take your pawn on a suicide mission. Beware of the blast radius.</Nod_Sbomb.description>


</LanguageData>